project/Function.py
project/Operations.py
project/__init__.py
project/__main__.py
ad_cs107-0.0.2.dist-info/.DS_Store
ad_cs107-0.0.2.dist-info/LICENSE
ad_cs107-0.0.2.dist-info/METADATA
ad_cs107-0.0.2.dist-info/WHEEL
ad_cs107-0.0.2.dist-info/top_level.txt
ad_cs107-0.0.2.dist-info/RECORD
